Workbook

Sheet Financials
A1: Kestrel Ridge Fabrication Holdings, Inc.
A2: Quarterly income statement data, $ in millions (unaudited)
A4: Line item | B4: Q4 2025 | C4: Q1 2026 | D4: Q2 2026 | E4: Q3 2026 | F4: LTM
A5: Revenue | B5: 120 | C5: 125 | D5: 130 | E5: 135 | F5: =SUM(B5:E5)
A6: Consolidated Net Income | B6: 3.5 | C6: 4 | D6: 5 | E6: 5.5 | F6: =SUM(B6:E6)
A7: Interest expense (total) | B7: 6 | C7: 6 | D7: 6 | E7: 6 | F7: =SUM(B7:E7)
A8: of which: cash interest | B8: 5.5 | C8: 5.5 | D8: 5.5 | E8: 5.5 | F8: =SUM(B8:E8)
A9: of which: amortization of fees / OID | B9: 0.5 | C9: 0.5 | D9: 0.5 | E9: 0.5 | F9: =SUM(B9:E9)
A10: Income tax expense | B10: 1.2 | C10: 1.4 | D10: 1.6 | E10: 1.8 | F10: =SUM(B10:E10)
A11: Depreciation and amortization | B11: 5.5 | C11: 5.5 | D11: 5.5 | E11: 5.5 | F11: =SUM(B11:E11)
A12: Non-cash stock-based compensation | B12: 0.5 | C12: 0.5 | D12: 0.5 | E12: 0.5 | F12: =SUM(B12:E12)
A13: Restructuring charges | B13: 1 | C13: 1.5 | D13: 2.5 | E13: 3 | F13: =SUM(B13:E13)
A16: Balance sheet items as of September 30, 2026 ($mm)
A17: Item | B17: Amount | C17: Notes
A18: Term Loan B | B18: 480 | C18: Senior secured
A19: Revolving Loans outstanding | B19: 35 | C19: $75mm commitment
A20: Finance Lease Obligations | B20: 5
A21: Letters of credit outstanding (undrawn) | B21: 6 | C21: Standby LCs
A22: Cash: operating accounts | B22: 23 | C22: Unrestricted
A23: Cash: money market funds | B23: 5 | C23: Unrestricted

Sheet Add-back Review
A1: Schedule 2 add-backs claimed by Borrower: eligibility review
A2: 18-month realization cutoff: | C2: 3/31/2028 (9/30/2026 + 18 months)
A4: # | B4: Clause | C4: Description | D4: Action status at 9/30/2026 | E4: Expected full realization | F4: Amount claimed ($mm) | G4: Eligible? | H4: Eligible amount ($mm)
A5: R-1 | B5: (vi) | C5: Severance, SG&A reduction program | D5: Completed | E5: n/a | F5: 4.5 | H5: =IF(G5="Yes",F5,IF(G5="No",0,""))
A6: R-2 | B6: (vi) | C6: Toledo warehouse lease exit costs | D6: Completed | E6: n/a | F6: 2 | H6: =IF(G6="Yes",F6,IF(G6="No",0,""))
A7: R-3 | B7: (vi) | C7: Relocation of welding line to Fort Wayne plant | D7: In progress | E7: n/a | F7: 1.5 | H7: =IF(G7="Yes",F7,IF(G7="No",0,""))
A8: S-1 | B8: (vii) | C8: Steel and aluminum procurement consolidation | D8: Initiated Q2 2026 | E8: Q2 2027 | F8: 6 | H8: =IF(G8="Yes",F8,IF(G8="No",0,""))
A9: S-2 | B9: (vii) | C9: SG&A headcount reduction run-rate savings | D9: Initiated Q3 2026 | E9: Q1 2027 | F9: 7 | H9: =IF(G9="Yes",F9,IF(G9="No",0,""))
A10: S-3 | B10: (vii) | C10: Dayton plant closure and consolidation | D10: Board approval expected Q4 2027 | E10: Q2 2028 | F10: 3 | H10: =IF(G10="Yes",F10,IF(G10="No",0,""))
C11: Total | F11: =SUM(F5:F10) | H11: =SUM(H5:H10)

Sheet Covenant Test
A1: Section 7.11 covenant recalculation: Test Period ended September 30, 2026 ($mm)
A2: Yellow cells = my inputs
A3: Line item | B3: Per Borrower certificate | C3: My recalculation | D3: Variance
A4: Consolidated Net Income | B4: 18 | C4: =Financials!F6 | D4: =IF(C4="","",C4-B4)
A5: (i) Consolidated Interest Expense | B5: 24 | C5: =Financials!F7 | D5: =IF(C5="","",C5-B5)
A6: (ii) Income tax expense | B6: 6 | C6: =Financials!F10 | D6: =IF(C6="","",C6-B6)
A7: (iii) Depreciation and amortization | B7: 22 | C7: =Financials!F11 | D7: =IF(C7="","",C7-B7)
A8: (iv) Non-cash stock-based compensation | B8: 2 | C8: =Financials!F12 | D8: =IF(C8="","",C8-B8)
A9: EBITDA before clauses (vi) and (vii) | B9: 72 | C9: =SUM(C4:C8) | D9: =IF(C9="","",C9-B9)
A10: (vi) Restructuring charges (eligible) | B10: 8 | C10: =IF(COUNTBLANK('Add-back Review'!G5:G10)>0,"",SUMIF('Add-back Review'!B5:B10,"(vi)",'Add-back Review'!H5:H10)) | D10: =IF(C10="","",C10-B10)
A11: (vii) Run-rate cost savings (eligible) | B11: 16 | C11: =IF(COUNTBLANK('Add-back Review'!G5:G10)>0,"",SUMIF('Add-back Review'!B5:B10,"(vii)",'Add-back Review'!H5:H10)) | D11: =IF(C11="","",C11-B11)
A12: Clauses (vi)+(vii) before cap | B12: 24 | C12: =IF(C11="","",C10+C11) | D12: =IF(C12="","",C12-B12)
A13: 25% cap | B13: 24 | D13: =IF(C13="","",C13-B13)
A14: Clauses (vi)+(vii) allowed | B14: 24 | C14: =IF(OR(C12="",C13=""),"",MIN(C12,C13)) | D14: =IF(C14="","",C14-B14)
A15: Consolidated EBITDA | B15: 96 | C15: =IF(C14="","",C9+C14) | D15: =IF(C15="","",C15-B15)
A17: Consolidated Total Debt (excl. undrawn LCs) | B17: 520 | C17: =Financials!B18+Financials!B19+Financials!B20 | D17: =IF(C17="","",C17-B17)
A18: Unrestricted cash | B18: 28 | C18: =Financials!B22+Financials!B23 | D18: =IF(C18="","",C18-B18)
A19: Cash netting allowed (cap $15.0mm) | B19: 28 | D19: =IF(C19="","",C19-B19)
A20: Consolidated Total Net Debt | B20: 492 | C20: =IF(C19="","",C17-C19) | D20: =IF(C20="","",C20-B20)
A22: Consolidated Cash Interest Expense | B22: 22 | C22: =Financials!F8 | D22: =IF(C22="","",C22-B22)
A24: Total Net Leverage Ratio | B24: 5.13 | C24: =IF(OR(C15="",C20=""),"",C20/C15) | D24: =IF(C24="","",C24-B24)
A25: Maximum permitted (FQ ending 9/30/2026) | B25: 5.25 | D25: =IF(C25="","",C25-B25)
A26: In compliance? | B26: Yes | C26: =IF(OR(C24="",C25=""),"",IF(C24<=C25,"Yes","No"))
A27: Interest Coverage Ratio | B27: 4.36 | C27: =IF(C15="","",C15/C22) | D27: =IF(C27="","",C27-B27)
A28: Minimum required | B28: 2.25 | C28: 2.25
A29: In compliance? | B29: Yes | C29: =IF(C27="","",IF(C27>=C28,"Yes","No"))
A31: EBITDA cushion / (shortfall) vs. leverage covenant | B31: 2.29 | C31: =IF(OR(C15="",C20="",C25=""),"",C15-C20/C25) | D31: =IF(C31="","",C31-B31)
A33: Equity cure analysis
A34: Consolidated EBITDA required for compliance | C34: =IF(OR(C20="",C25=""),"",C20/C25)
A35: Minimum Cure Amount | C35: =IF(OR(C34="",C15=""),"",C34-C15)
A36: Cure Amount (rounded up to $0.1mm)
A37: Pro forma Total Net Leverage Ratio | C37: =IF(C36="","",C20/(C15+C36))
A38: Cure permitted under 8.04(b)?
